{
   "results" : [
      {
         "address_components" : [
            {
               "long_name" : "Salzburg",
               "short_name" : "Salzburg",
               "types" : [ "locality", "political" ]
            },
            {
               "long_name" : "Salzburg",
               "short_name" : "Salzburg",
               "types" : [ "administrative_area_level_2", "political" ]
            },
            {
               "long_name" : "Salzburg",
               "short_name" : "Salzburg",
               "types" : [ "administrative_area_level_1", "political" ]
            },
            {
               "long_name" : "Austria",
               "short_name" : "AT",
               "types" : [ "country", "political" ]
            }
         ],
         "formatted_address" : "Salzburg, Austria",
         "geometry" : {
            "bounds" : {
               "northeast" : {
                  "lat" : 47.85431,
                  "lng" : 13.1268799
               },
               "southwest" : {
                  "lat" : 47.75131,
                  "lng" : 12.9859801
               }
            },
            "location" : {
               "lat" : 47.80949,
               "lng" : 13.05501
            },
            "location_type" : "APPROXIMATE",
            "viewport" : {
               "northeast" : {
                  "lat" : 47.85431,
                  "lng" : 13.1268799
               },
               "southwest" : {
                  "lat" : 47.75131,
                  "lng" : 12.9859801
               }
            }
         },
         "place_id" : "ChIJsdQIqd2adkcRPfcqQaGD4cE",
         "types" : [ "locality", "political" ]
      }
   ],
   "status" : "OK"
}
