{
   "results" : [
      {
         "address_components" : [
            {
               "long_name" : "El Seibo",
               "short_name" : "El Seibo",
               "types" : [ "locality", "political" ]
            },
            {
               "long_name" : "El Seibo",
               "short_name" : "El Seibo",
               "types" : [ "administrative_area_level_2", "political" ]
            },
            {
               "long_name" : "El Seibo Province",
               "short_name" : "El Seibo Province",
               "types" : [ "administrative_area_level_1", "political" ]
            },
            {
               "long_name" : "Dominican Republic",
               "short_name" : "DO",
               "types" : [ "country", "political" ]
            },
            {
               "long_name" : "24000",
               "short_name" : "24000",
               "types" : [ "postal_code" ]
            }
         ],
         "formatted_address" : "El Seibo 24000, Dominican Republic",
         "geometry" : {
            "bounds" : {
               "northeast" : {
                  "lat" : 18.7788351,
                  "lng" : -69.0306616
               },
               "southwest" : {
                  "lat" : 18.7496595,
                  "lng" : -69.0513898
               }
            },
            "location" : {
               "lat" : 18.7653036,
               "lng" : -69.0389048
            },
            "location_type" : "APPROXIMATE",
            "viewport" : {
               "northeast" : {
                  "lat" : 18.7788351,
                  "lng" : -69.0306616
               },
               "southwest" : {
                  "lat" : 18.7496595,
                  "lng" : -69.0513898
               }
            }
         },
         "place_id" : "ChIJ70e-hVk2r44RTKl9CppyCC4",
         "types" : [ "locality", "political" ]
      }
   ],
   "status" : "OK"
}
