{
   "results" : [
      {
         "address_components" : [
            {
               "long_name" : "North Khorasan Province",
               "short_name" : "North Khorasan Province",
               "types" : [ "administrative_area_level_1", "political" ]
            },
            {
               "long_name" : "Iran",
               "short_name" : "IR",
               "types" : [ "country", "political" ]
            }
         ],
         "formatted_address" : "North Khorasan Province, Iran",
         "geometry" : {
            "bounds" : {
               "northeast" : {
                  "lat" : 38.286124,
                  "lng" : 58.387249
               },
               "southwest" : {
                  "lat" : 36.6166539,
                  "lng" : 55.805023
               }
            },
            "location" : {
               "lat" : 37.4710353,
               "lng" : 57.10131879999999
            },
            "location_type" : "APPROXIMATE",
            "viewport" : {
               "northeast" : {
                  "lat" : 38.286124,
                  "lng" : 58.387249
               },
               "southwest" : {
                  "lat" : 36.6166539,
                  "lng" : 55.805023
               }
            }
         },
         "place_id" : "ChIJJScSl5qwcD8RHz6uVTPV7JM",
         "types" : [ "administrative_area_level_1", "political" ]
      }
   ],
   "status" : "OK"
}
