{
   "results" : [
      {
         "address_components" : [
            {
               "long_name" : "Vibo Valentia",
               "short_name" : "Vibo Valentia",
               "types" : [ "locality", "political" ]
            },
            {
               "long_name" : "Vibo Valentia",
               "short_name" : "Vibo Valentia",
               "types" : [ "administrative_area_level_3", "political" ]
            },
            {
               "long_name" : "Province of Vibo Valentia",
               "short_name" : "VV",
               "types" : [ "administrative_area_level_2", "political" ]
            },
            {
               "long_name" : "Calabria",
               "short_name" : "Calabria",
               "types" : [ "administrative_area_level_1", "political" ]
            },
            {
               "long_name" : "Italy",
               "short_name" : "IT",
               "types" : [ "country", "political" ]
            },
            {
               "long_name" : "89900",
               "short_name" : "89900",
               "types" : [ "postal_code" ]
            }
         ],
         "formatted_address" : "89900 Vibo Valentia, Province of Vibo Valentia, Italy",
         "geometry" : {
            "bounds" : {
               "northeast" : {
                  "lat" : 38.6929198,
                  "lng" : 16.1277849
               },
               "southwest" : {
                  "lat" : 38.6645713,
                  "lng" : 16.0756393
               }
            },
            "location" : {
               "lat" : 38.6757774,
               "lng" : 16.0983488
            },
            "location_type" : "APPROXIMATE",
            "viewport" : {
               "northeast" : {
                  "lat" : 38.6929198,
                  "lng" : 16.1277849
               },
               "southwest" : {
                  "lat" : 38.6645713,
                  "lng" : 16.0756393
               }
            }
         },
         "place_id" : "ChIJjePSsI1oFRMRJ0Z3tt50jEw",
         "types" : [ "locality", "political" ]
      }
   ],
   "status" : "OK"
}
