{
   "results" : [
      {
         "address_components" : [
            {
               "long_name" : "Aichi",
               "short_name" : "Aichi",
               "types" : [ "administrative_area_level_1", "political" ]
            },
            {
               "long_name" : "Japan",
               "short_name" : "JP",
               "types" : [ "country", "political" ]
            }
         ],
         "formatted_address" : "Aichi, Japan",
         "geometry" : {
            "bounds" : {
               "northeast" : {
                  "lat" : 35.4247423,
                  "lng" : 137.8381715
               },
               "southwest" : {
                  "lat" : 34.5734971,
                  "lng" : 136.6710078
               }
            },
            "location" : {
               "lat" : 35.0182505,
               "lng" : 137.2923893
            },
            "location_type" : "APPROXIMATE",
            "viewport" : {
               "northeast" : {
                  "lat" : 35.4247423,
                  "lng" : 137.8381715
               },
               "southwest" : {
                  "lat" : 34.5734971,
                  "lng" : 136.6710078
               }
            }
         },
         "place_id" : "ChIJ5zKTSdW6BGARp0EVGF2mX-s",
         "types" : [ "administrative_area_level_1", "political" ]
      }
   ],
   "status" : "OK"
}
