{
   "results" : [
      {
         "address_components" : [
            {
               "long_name" : "Mokhotlong",
               "short_name" : "Mokhotlong",
               "types" : [ "locality", "political" ]
            },
            {
               "long_name" : "Mokhotlong",
               "short_name" : "Mokhotlong",
               "types" : [ "administrative_area_level_1", "political" ]
            },
            {
               "long_name" : "Lesotho",
               "short_name" : "LS",
               "types" : [ "country", "political" ]
            }
         ],
         "formatted_address" : "Mokhotlong, Lesotho",
         "geometry" : {
            "bounds" : {
               "northeast" : {
                  "lat" : -29.2750633,
                  "lng" : 29.0821563
               },
               "southwest" : {
                  "lat" : -29.2995091,
                  "lng" : 29.0297267
               }
            },
            "location" : {
               "lat" : -29.2875557,
               "lng" : 29.06053889999999
            },
            "location_type" : "APPROXIMATE",
            "viewport" : {
               "northeast" : {
                  "lat" : -29.2750633,
                  "lng" : 29.0821563
               },
               "southwest" : {
                  "lat" : -29.2995091,
                  "lng" : 29.0297267
               }
            }
         },
         "place_id" : "ChIJ1dcqmBIV8x4Rx8lhwfyfsWc",
         "types" : [ "locality", "political" ]
      }
   ],
   "status" : "OK"
}
