{
   "results" : [
      {
         "address_components" : [
            {
               "long_name" : "Kriva Palanka",
               "short_name" : "Kriva Palanka",
               "types" : [ "locality", "political" ]
            },
            {
               "long_name" : "Municipality of Kriva Palanka",
               "short_name" : "Municipality of Kriva Palanka",
               "types" : [ "administrative_area_level_1", "political" ]
            },
            {
               "long_name" : "North Macedonia",
               "short_name" : "MK",
               "types" : [ "country", "political" ]
            }
         ],
         "formatted_address" : "Kriva Palanka, North Macedonia",
         "geometry" : {
            "bounds" : {
               "northeast" : {
                  "lat" : 42.2233612,
                  "lng" : 22.3575425
               },
               "southwest" : {
                  "lat" : 42.1902456,
                  "lng" : 22.3109686
               }
            },
            "location" : {
               "lat" : 42.2058454,
               "lng" : 22.3307965
            },
            "location_type" : "APPROXIMATE",
            "viewport" : {
               "northeast" : {
                  "lat" : 42.2233612,
                  "lng" : 22.3575425
               },
               "southwest" : {
                  "lat" : 42.1902456,
                  "lng" : 22.3109686
               }
            }
         },
         "place_id" : "ChIJkQU1JMV1VRMRhJiQYzNxHpM",
         "types" : [ "locality", "political" ]
      }
   ],
   "status" : "OK"
}
