{
   "results" : [
      {
         "address_components" : [
            {
               "long_name" : "Tolmin",
               "short_name" : "Tolmin",
               "types" : [ "locality", "political" ]
            },
            {
               "long_name" : "Tolmin",
               "short_name" : "Tolmin",
               "types" : [ "postal_town" ]
            },
            {
               "long_name" : "Tolmin",
               "short_name" : "Tolmin",
               "types" : [ "administrative_area_level_1", "political" ]
            },
            {
               "long_name" : "Slovenia",
               "short_name" : "SI",
               "types" : [ "country", "political" ]
            },
            {
               "long_name" : "5220",
               "short_name" : "5220",
               "types" : [ "postal_code" ]
            }
         ],
         "formatted_address" : "5220 Tolmin, Slovenia",
         "geometry" : {
            "bounds" : {
               "northeast" : {
                  "lat" : 46.19265799999999,
                  "lng" : 13.7411589
               },
               "southwest" : {
                  "lat" : 46.1730367,
                  "lng" : 13.7133538
               }
            },
            "location" : {
               "lat" : 46.1857188,
               "lng" : 13.7319838
            },
            "location_type" : "APPROXIMATE",
            "viewport" : {
               "northeast" : {
                  "lat" : 46.19265799999999,
                  "lng" : 13.7411589
               },
               "southwest" : {
                  "lat" : 46.1730367,
                  "lng" : 13.7133538
               }
            }
         },
         "place_id" : "ChIJlVJqMcj3ekcRefAW6QkRd7k",
         "types" : [ "locality", "political" ]
      }
   ],
   "status" : "OK"
}
