{
   "results" : [
      {
         "address_components" : [
            {
               "long_name" : "Sedhiou",
               "short_name" : "Sedhiou",
               "types" : [ "locality", "political" ]
            },
            {
               "long_name" : "Sédhiou Region",
               "short_name" : "Sédhiou Region",
               "types" : [ "administrative_area_level_1", "political" ]
            },
            {
               "long_name" : "Senegal",
               "short_name" : "SN",
               "types" : [ "country", "political" ]
            }
         ],
         "formatted_address" : "Sedhiou, Senegal",
         "geometry" : {
            "bounds" : {
               "northeast" : {
                  "lat" : 12.7190515,
                  "lng" : -15.5490875
               },
               "southwest" : {
                  "lat" : 12.6899976,
                  "lng" : -15.5705882
               }
            },
            "location" : {
               "lat" : 12.704604,
               "lng" : -15.5562304
            },
            "location_type" : "APPROXIMATE",
            "viewport" : {
               "northeast" : {
                  "lat" : 12.7190515,
                  "lng" : -15.5490875
               },
               "southwest" : {
                  "lat" : 12.6899976,
                  "lng" : -15.5705882
               }
            }
         },
         "place_id" : "ChIJIXMJuAs45g4RsmQcfxDjSMA",
         "types" : [ "locality", "political" ]
      }
   ],
   "status" : "OK"
}
