{
   "results" : [
      {
         "address_components" : [
            {
               "long_name" : "Daraa",
               "short_name" : "Daraa",
               "types" : [ "locality", "political" ]
            },
            {
               "long_name" : "Daraa District",
               "short_name" : "Daraa District",
               "types" : [ "administrative_area_level_2", "political" ]
            },
            {
               "long_name" : "Daraa Governorate",
               "short_name" : "Daraa Governorate",
               "types" : [ "administrative_area_level_1", "political" ]
            },
            {
               "long_name" : "Syria",
               "short_name" : "SY",
               "types" : [ "country", "political" ]
            }
         ],
         "formatted_address" : "Daraa, Syria",
         "geometry" : {
            "bounds" : {
               "northeast" : {
                  "lat" : 32.6497446,
                  "lng" : 36.1277676
               },
               "southwest" : {
                  "lat" : 32.5959628,
                  "lng" : 36.071132
               }
            },
            "location" : {
               "lat" : 32.626434,
               "lng" : 36.1033061
            },
            "location_type" : "APPROXIMATE",
            "viewport" : {
               "northeast" : {
                  "lat" : 32.6497446,
                  "lng" : 36.1277676
               },
               "southwest" : {
                  "lat" : 32.5959628,
                  "lng" : 36.071132
               }
            }
         },
         "place_id" : "ChIJ5db649vtGxURdgVqTWRMfWI",
         "types" : [ "locality", "political" ]
      }
   ],
   "status" : "OK"
}
